Workbook

Sheet Vendas
A1: DREE MAQUIAGEM · Planner Financeiro
A2: Registro de vendas — preencha as colunas claras. O lucro é calculado sozinho. 💜
A4: Data | B4: Cliente | C4: Produto | D4: Custo (R$) | E4: Venda (R$) | F4: Qtd | G4: Total (R$) | H4: Lucro (R$) | I4: Pagamento
G5: =IF(E5<>"",E5*IF(F5="",1,F5),"") | H5: =IF(AND(D5<>"",E5<>""),(E5-D5)*IF(F5="",1,F5),"")
G6: =IF(E6<>"",E6*IF(F6="",1,F6),"") | H6: =IF(AND(D6<>"",E6<>""),(E6-D6)*IF(F6="",1,F6),"")
G7: =IF(E7<>"",E7*IF(F7="",1,F7),"") | H7: =IF(AND(D7<>"",E7<>""),(E7-D7)*IF(F7="",1,F7),"")
G8: =IF(E8<>"",E8*IF(F8="",1,F8),"") | H8: =IF(AND(D8<>"",E8<>""),(E8-D8)*IF(F8="",1,F8),"")
G9: =IF(E9<>"",E9*IF(F9="",1,F9),"") | H9: =IF(AND(D9<>"",E9<>""),(E9-D9)*IF(F9="",1,F9),"")
G10: =IF(E10<>"",E10*IF(F10="",1,F10),"") | H10: =IF(AND(D10<>"",E10<>""),(E10-D10)*IF(F10="",1,F10),"")
G11: =IF(E11<>"",E11*IF(F11="",1,F11),"") | H11: =IF(AND(D11<>"",E11<>""),(E11-D11)*IF(F11="",1,F11),"")
G12: =IF(E12<>"",E12*IF(F12="",1,F12),"") | H12: =IF(AND(D12<>"",E12<>""),(E12-D12)*IF(F12="",1,F12),"")
G13: =IF(E13<>"",E13*IF(F13="",1,F13),"") | H13: =IF(AND(D13<>"",E13<>""),(E13-D13)*IF(F13="",1,F13),"")
G14: =IF(E14<>"",E14*IF(F14="",1,F14),"") | H14: =IF(AND(D14<>"",E14<>""),(E14-D14)*IF(F14="",1,F14),"")
G15: =IF(E15<>"",E15*IF(F15="",1,F15),"") | H15: =IF(AND(D15<>"",E15<>""),(E15-D15)*IF(F15="",1,F15),"")
G16: =IF(E16<>"",E16*IF(F16="",1,F16),"") | H16: =IF(AND(D16<>"",E16<>""),(E16-D16)*IF(F16="",1,F16),"")
... G44: =IF(E44<>"",E44*IF(F44="",1,F44),"") | H44: =IF(AND(D44<>"",E44<>""),(E44-D44)*IF(F44="",1,F44),"")
A45: TOTAIS DO MÊS | G45: =SUM(G5:G44) | H45: =SUM(H5:H44)

Sheet Resumo
B2: Resumo do mês 💜
B4: Faturamento total | C4: =Vendas!G45
B5: Lucro total | C5: =Vendas!H45
B6: Custo total | C6: =Vendas!G45-Vendas!H45
B7: Nº de vendas | C7: =COUNT(Vendas!G5:Vendas!G44)
B8: Ticket médio (R$) | C8: =IFERROR(Vendas!G45/COUNT(Vendas!G5:Vendas!G44),0)
B9: Margem de lucro (%) | C9: =IFERROR(Vendas!H45/Vendas!G45,0)
B11: 🎯 Minha meta de lucro do mês
B12: Meta (edite aqui): | C12: 500
B13: Quanto falta: | C13: =MAX(C12-Vendas!H45,0)
B14: % da meta atingida: | C14: =IFERROR(Vendas!H45/C12,0)
B16: Dica: preencha a aba "Vendas" a cada venda. Aqui tudo atualiza sozinho.
